{
  "required": true,
  "minVersion": "0.8",
  "package": "net.ccbluex.liquidbounce.injection.mixins",
  "compatibilityLevel": "JAVA_8",
  "mixins": [],
  "client": [
    "minecraft.block.MixinCactusBlock",
    "minecraft.block.MixinFluidBlock",
    "minecraft.client.MixinKeyboard",
    "minecraft.client.MixinMinecraftClient",
    "minecraft.entity.MixinClientPlayerEntity",
    "minecraft.entity.MixinEntity",
    "minecraft.gui.MixinInGameHud",
    "minecraft.gui.MixinScreen",
    "minecraft.network.MixinClientConnection",
    "minecraft.network.MixinClientPlayerInteractionManager",
    "minecraft.render.MixinGameRenderer"
  ],
  "server": [],
  "injectors": {
    "defaultRequire": 1
  }
}